Metadata-Version: 2.1
Name: odoo14-addon-l10n-it-fatturapa-out-stamp
Version: 14.0.1.0.1
Summary: Modulo ponte tra emissione fatture elettroniche e imposta di bollo
Home-page: https://github.com/OCA/l10n-italy
Author: Agile Business Group, Odoo Community Association (OCA)
Author-email: support@odoo-community.org
License: AGPL-3
Platform: UNKNOWN
Classifier: Programming Language :: Python
Classifier: Framework :: Odoo
Classifier: Framework :: Odoo :: 14.0
Classifier: License :: OSI Approved :: GNU Affero General Public License v3
Classifier: Development Status :: 4 - Beta
Requires-Python: >=3.6
Requires-Dist: odoo14-addon-l10n-it-account-stamp
Requires-Dist: odoo14-addon-l10n-it-fatturapa-out
Requires-Dist: odoo <14.1dev,>=14.0a
